{
  "hyprlock-text-color": "cdd6f4",
  "qs-txt2": "#aaaaaa",
  "hyprlock-battery-color": "7cafc2",
  "qs-disk": "#7cafc2",
  "nvim-colorscheme": "gruvbox",
  "qs-mmry": "#59cd90",
  "gtk-theme": "Kripton",
  "hyprlock-minutes-color": "ba8baf",
  "qs-idle": "#ba8baf",
  "accent-color": "141414",
  "starship-palette": "mavenblack",
  "qs-powr": "#f7ca88",
  "text-color": "eeeeee",
  "qs-bat4": "#f7ca88",
  "bg-color-tr": "test",
  "qs-name": "#eeeeee",
  "qs-bat2": "#59cd90",
  "qs-cpuc": "#ba8baf",
  "qs-uptm": "#a1b56c",
  "qs-sptr": "#585b70",
  "qs-acct": "#cba6f7",
  "qs-txt1": "#eeeeee",
  "hyprlock-hour-color": "59cd90",
  "qs-wksp": "#eeeeee",
  "qs-bgnd": "\"#141414\"",
  "qs-wifi": "#f7ca88",
  "qs-dstr": "#7cafc2",
  "hyprlock-uptime-color": "a1b56c",
  "rofi-bg-color-tr": "hsla(0, 0, 0%, 50%)",
  "qs-pfle": "#59cd90",
  "dark-bg-color": "000000",
  "ghostty_theme": "MavenBlack",
  "waybar-color": "blue",
  "qs-bglt": "#eeeeee",
  "icon-theme": "Cosmic",
  "qs-clck": "#eeeeee",
  "qs-bat1": "#a1b56c",
  "bg-color": "141414",
  "qs-bat3": "#7cafc2",
  "qs-bat5": "#ab4642"
}