{
  "icon-theme": "gruvbox_dark",
  "qs-bat5": "#eeeeee",
  "hyprlock-minutes-color": "eeeeee",
  "starship-palette": "mavenblack",
  "qs-pfle": "#eeeeee",
  "qs-bat1": "#eeeeee",
  "qs-bat3": "#eeeeee",
  "accent-color": "59cd90",
  "text-color": "eeeeee",
  "hyprlock-text-color": "cdd6f4",
  "qs-mmry": "#eeeeee",
  "qs-disk": "#eeeeee",
  "qs-bat2": "#eeeeee",
  "qs-idle": "#eeeeee",
  "hyprlock-hour-color": "eeeeee",
  "qs-bgnd": "\"#000000\"",
  "hyprlock-uptime-color": "eeeeee",
  "qs-acct": "#cba6f7",
  "qs-cpuc": "#eeeeee",
  "qs-bglt": "#eeeeee",
  "qs-txt2": "#aaaaaa",
  "bg-color": "000000",
  "qs-dstr": "#eeeeee",
  "qs-wifi": "#eeeeee",
  "nvim-colorscheme": "gruvbox",
  "qs-powr": "#eeeeee",
  "qs-wksp": "#000000",
  "rofi-bg-color-tr": "hsla(0, 0, 0%, 50%)",
  "qs-uptm": "#eeeeee",
  "hyprlock-battery-color": "eeeeee",
  "ghostty_theme": "MavenBlack",
  "qs-sptr": "#585b70",
  "qs-bat4": "#eeeeee",
  "gtk-theme": "Gruvbox-Yellow-Dark",
  "bg-color-tr": "test",
  "qs-clck": "#eeeeee",
  "qs-txt1": "#eeeeee",
  "waybar-color": "blue",
  "qs-name": "#eeeeee",
  "dark-bg-color": "000000"
}